pymessari/__init__.py
pymessari/asset.py
pymessari/base.py
pymessari/market.py
pymessari/news.py
pymessari/protocol.py
pymessari/pymessari.py
pymessari/timeseries.py
pymessari-0.2.0.dist-info/LICENSE
pymessari-0.2.0.dist-info/METADATA
pymessari-0.2.0.dist-info/WHEEL
pymessari-0.2.0.dist-info/top_level.txt
pymessari-0.2.0.dist-info/RECORD
