Metadata-Version: 2.1
Name: pymessari
Version: 0.2.0
Summary: client library for messari api
Home-page: https://github.com/nxt-fintech/pymessari
Author: Next Finance Tech
License: APACHE LICENSE, VERSION 2.0
Keywords: messari
Classifier: Programming Language :: Python
License-File: LICENSE
Requires-Dist: requests
